pypop7/benchmarks/__init__.py
pypop7/benchmarks/_generate_rotation_matrix.py
pypop7/benchmarks/_generate_shift_vector.py
pypop7/benchmarks/_test_coco.py
pypop7/benchmarks/_test_pygmo.py
pypop7/benchmarks/base_functions.py
pypop7/benchmarks/cases.py
pypop7/benchmarks/coco.py
pypop7/benchmarks/continuous_functions.py
pypop7/benchmarks/data_science.py
pypop7/benchmarks/gymnasium.py
pypop7/benchmarks/lbo.py
pypop7/benchmarks/never_grad.py
pypop7/benchmarks/pygmo.py
pypop7/benchmarks/rotated_functions.py
pypop7/benchmarks/shifted_functions.py
pypop7/benchmarks/test_base_functions.py
pypop7/benchmarks/test_continuous_functions.py
pypop7/benchmarks/test_data_science.py
pypop7/benchmarks/test_gymnasium.py
pypop7/benchmarks/test_lbo.py
pypop7/benchmarks/test_never_grad.py
pypop7/benchmarks/test_rotated_functions.py
pypop7/benchmarks/test_shifted_functions.py
pypop7/benchmarks/test_utils.py
pypop7/benchmarks/utils.py
pypop7/optimizers/bo/__init__.py
pypop7/optimizers/bo/_repeat_lamcts.py
pypop7/optimizers/bo/_test_lamcts.py
pypop7/optimizers/bo/bo.py
pypop7/optimizers/bo/lamcts.py
pypop7/optimizers/bo/test_bo.py
pypop7/optimizers/bo/test_lamcts.py
pypop7/optimizers/cc/__init__.py
pypop7/optimizers/cc/_repeat_coea.py
pypop7/optimizers/cc/_repeat_cosyne.py
pypop7/optimizers/cc/_test_cocma.py
pypop7/optimizers/cc/_test_coea.py
pypop7/optimizers/cc/_test_cosyne.py
pypop7/optimizers/cc/_test_hcc.py
pypop7/optimizers/cc/cc.py
pypop7/optimizers/cc/cocma.py
pypop7/optimizers/cc/coea.py
pypop7/optimizers/cc/cosyne.py
pypop7/optimizers/cc/hcc.py
pypop7/optimizers/cc/test_cc.py
pypop7/optimizers/cc/test_cocma.py
pypop7/optimizers/cc/test_coea.py
pypop7/optimizers/cc/test_cosyne.py
pypop7/optimizers/cc/test_hcc.py
pypop7/optimizers/cem/__init__.py
pypop7/optimizers/cem/_repeat_dcem.py
pypop7/optimizers/cem/_repeat_dscem.py
pypop7/optimizers/cem/_repeat_mras.py
pypop7/optimizers/cem/_repeat_scem.py
pypop7/optimizers/cem/_test_dcem.py
pypop7/optimizers/cem/_test_dscem.py
pypop7-0.0.82.dist-info/LICENSE
pypop7-0.0.82.dist-info/METADATA
pypop7-0.0.82.dist-info/WHEEL
pypop7-0.0.82.dist-info/top_level.txt
pypop7-0.0.82.dist-info/RECORD
