Metadata-Version: 2.1
Name: pypop7
Version: 0.0.82
Summary: pypop7 (Pure-PYthon library of POPulation-based OPtimization)
Home-page: https://github.com/Evolutionary-Intelligence/pypop
Author: Evolutionary-Intelligence (@HIT&SUSTech)
Author-email: 11749325@mail.sustech.edu.cn
Project-URL: Bug Tracker, https://github.com/Evolutionary-Intelligence/pypop/issues
Classifier: Programming Language :: Python :: 3
Classifier: License :: OSI Approved :: GNU General Public License v3 or later (GPLv3+)
Classifier: Operating System :: OS Independent
Requires-Python: >=3.5
License-File: LICENSE
Requires-Dist: numpy
Requires-Dist: scipy
Requires-Dist: scikit-learn
Requires-Dist: numba
Requires-Dist: matplotlib
Requires-Dist: seaborn
Requires-Dist: celluloid
Requires-Dist: imageio
Requires-Dist: requests
Requires-Dist: nevergrad
Requires-Dist: gymnasium
Requires-Dist: gymnasium[classic-control]
